cloudtemplatemanager/__init__.py
cloudtemplatemanager/__main__.py
cloudtemplatemanager/base.py
cloudtemplatemanager/provision.py
cloudtemplatemanager/stack.py
cloudtemplatemanager-1.0.0.dist-info/DESCRIPTION.rst
cloudtemplatemanager-1.0.0.dist-info/entry_points.txt
cloudtemplatemanager-1.0.0.dist-info/METADATA
cloudtemplatemanager-1.0.0.dist-info/metadata.json
cloudtemplatemanager-1.0.0.dist-info/RECORD
cloudtemplatemanager-1.0.0.dist-info/top_level.txt
cloudtemplatemanager-1.0.0.dist-info/WHEEL
