Metadata-Version: 2.0
Name: cloudtemplatemanager
Version: 1.0.0
Summary: Utility to manager the uploading and provisioning of resource templates
Home-page: https://github.com/drewsonne/cloudtemplatemanager
Author: Drew J. Sonne
Author-email: drew.sonne@gmail.com
License: GPLv2
Platform: UNKNOWN
Requires-Dist: typing
Requires-Dist: aws-auth-helper
Requires-Dist: boto3
Requires-Dist: pyaml
Requires-Dist: voluptuous
